odoo/addons/l10n_it_fatturapa_import_zip_in_rc/README.rst
odoo/addons/l10n_it_fatturapa_import_zip_in_rc/__init__.py
odoo/addons/l10n_it_fatturapa_import_zip_in_rc/__manifest__.py
odoo/addons/l10n_it_fatturapa_import_zip_in_rc/i18n/it.po
odoo/addons/l10n_it_fatturapa_import_zip_in_rc/i18n/l10n_it_fatturapa_import_zip_in_rc.pot
odoo/addons/l10n_it_fatturapa_import_zip_in_rc/readme/CONTRIBUTORS.md
odoo/addons/l10n_it_fatturapa_import_zip_in_rc/readme/DESCRIPTION.md
odoo/addons/l10n_it_fatturapa_import_zip_in_rc/static/description/icon.png
odoo/addons/l10n_it_fatturapa_import_zip_in_rc/static/description/index.html
odoo/addons/l10n_it_fatturapa_import_zip_in_rc/tests/__init__.py
odoo/addons/l10n_it_fatturapa_import_zip_in_rc/tests/test_import_zip.py
odoo/addons/l10n_it_fatturapa_import_zip_in_rc/tests/data/IT01234567890_FPR04.zip
odoo/addons/l10n_it_fatturapa_import_zip_in_rc/wizards/__init__.py
odoo/addons/l10n_it_fatturapa_import_zip_in_rc/wizards/wizard_import_fatturapa.py
odoo_addon_l10n_it_fatturapa_import_zip_in_rc-16.0.1.0.0.4.dist-info/METADATA
odoo_addon_l10n_it_fatturapa_import_zip_in_rc-16.0.1.0.0.4.dist-info/WHEEL
odoo_addon_l10n_it_fatturapa_import_zip_in_rc-16.0.1.0.0.4.dist-info/top_level.txt
odoo_addon_l10n_it_fatturapa_import_zip_in_rc-16.0.1.0.0.4.dist-info/RECORD
