Metadata-Version: 2.1
Name: odoo-addon-l10n_it_fatturapa_import_zip_in_rc
Version: 16.0.1.0.0.4
Requires-Python: >=3.10
Requires-Dist: odoo-addon-l10n_it_fatturapa_import_zip>=16.0dev,<16.1dev
Requires-Dist: odoo-addon-l10n_it_fatturapa_in_rc>=16.0dev,<16.1dev
Requires-Dist: odoo>=16.0a,<16.1dev
Summary: Importare fatture elettroniche con inversione contabile da un file ZIP.
Home-page: https://github.com/OCA/l10n-italy
License: AGPL-3
Author: Aion Tech, Odoo Community Association (OCA)
Author-email: support@odoo-community.org
Classifier: Programming Language :: Python
Classifier: Framework :: Odoo
Classifier: Framework :: Odoo :: 16.0
Classifier: License :: OSI Approved :: GNU Affero General Public License v3
